jimner/__init__.py
jimner/jimner.py
jimner/fonts/1Row.json
jimner/fonts/3-D.json
jimner/fonts/3D Diagonal.json
jimner/fonts/3D-ASCII.json
jimner/fonts/3x5.json
jimner/fonts/4Max.json
jimner/fonts/5 Line Oblique.json
jimner/fonts/AMC 3 Line.json
jimner/fonts/AMC 3 Liv1.json
jimner/fonts/AMC AAA01.json
jimner/fonts/AMC Neko.json
jimner/fonts/AMC Razor.json
jimner/fonts/AMC Razor2.json
jimner/fonts/AMC Slash.json
jimner/fonts/AMC Slider.json
jimner/fonts/AMC Thin.json
jimner/fonts/AMC Tubes.json
jimner/fonts/AMC Untitled.json
jimner/fonts/ANSI Shadow.json
jimner/fonts/ASCII New Roman.json
jimner/fonts/Abraxis-Big.json
jimner/fonts/Abraxis-Small.json
jimner/fonts/Acrobatic.json
jimner/fonts/Alligator.json
jimner/fonts/Alligator2.json
jimner/fonts/Alpha.json
jimner/fonts/Alphabet.json
jimner/fonts/Arrows.json
jimner/fonts/Avatar.json
jimner/fonts/Banner.json
jimner/fonts/Banner3-D.json
jimner/fonts/Banner3.json
jimner/fonts/Banner4.json
jimner/fonts/Barbwire.json
jimner/fonts/Basic.json
jimner/fonts/Bear.json
jimner/fonts/Bell.json
jimner/fonts/Benjamin.json
jimner/fonts/Bent.json
jimner/fonts/Big Chief.json
jimner/fonts/Big Money-ne.json
jimner/fonts/Big Money-nw.json
jimner/fonts/Big Money-se.json
jimner/fonts/Big Money-sw.json
jimner/fonts/Big.json
jimner/fonts/Bigfig.json
jimner/fonts/Binary.json
jimner/fonts/Blest.json
jimner/fonts/Block.json
jimner/fonts/Blocks.json
jimner/fonts/Bloody.json
jimner/fonts/Boie.json
jimner/fonts/Boie2.json
jimner/fonts/Bolger.json
jimner/fonts/Bone's Font.json
jimner/fonts/Braced.json
jimner/fonts/Bright.json
jimner/fonts/Broadway KB.json
jimner/fonts/Broadway.json
jimner/fonts/Bubble.json
jimner/fonts/Bulbhead.json
jimner/fonts/CaMiZ.json
jimner/fonts/Caligraphy.json
jimner/fonts/Caligraphy2.json
jimner/fonts/Calvin S.json
jimner/fonts/Cards.json
jimner/fonts/Catwalk.json
jimner/fonts/CeA.json
jimner/fonts/CeA2.json
jimner/fonts/Cheese.json
jimner/fonts/Chiseled.json
jimner/fonts/Chunky.json
jimner/fonts/Coinstak.json
jimner-1.2.3.dist-info/LICENSE
jimner-1.2.3.dist-info/METADATA
jimner-1.2.3.dist-info/WHEEL
jimner-1.2.3.dist-info/top_level.txt
jimner-1.2.3.dist-info/RECORD
