Metadata-Version: 2.1
Name: jimner
Version: 1.2.3
Summary: A banner generating library for UNIX, LINUX, MAC-OS and WINDOWS
Home-page: https://github.com/Jimut123/jimner
Author: Jimut Bahan Pal
Author-email: jimutbahanpal@yahoo.com
License: UNKNOWN
Platform: UNKNOWN
Classifier: Programming Language :: Python :: 3
Classifier: License :: OSI Approved :: MIT License
Classifier: Operating System :: OS Independent
